saywoof/__init__.py
saywoof/main.py
saywoof-0.1.0.dist-info/METADATA
saywoof-0.1.0.dist-info/WHEEL
saywoof-0.1.0.dist-info/entry_points.txt
saywoof-0.1.0.dist-info/top_level.txt
saywoof-0.1.0.dist-info/RECORD
